nurmoai/__init__.py
nurmoai/nurmoai.py
nurmoai-1.0.3.dist-info/METADATA
nurmoai-1.0.3.dist-info/WHEEL
nurmoai-1.0.3.dist-info/top_level.txt
nurmoai-1.0.3.dist-info/RECORD
