Metadata-Version: 2.1
Name: nurmoai
Version: 1.0.3
Summary: A Python client for the NurmoAI API.
Home-page: https://nurmo.app
Author: Reksely
Author-email: reksely@gmail.com
Requires-Dist: requests >=2.25.1
